{"chain": [["W", 1, "var", 1], ["I", 0, "a", 1], ["R", 1, ",", 1], ["I", 1, "b", 1], ["R", 3, ":", 1], ["W", 3, "integer", 1], ["R", 4, ";", 1], ["I", 2, "cs", 2], ["R", 3, ":", 2], ["W", 7, "array", 2], ["R", 7, "[", 2], ["C", 0, "0", 2], ["R", 2, "..", 2], ["C", 1, "20", 2], ["R", 1, ",", 2], ["C", 2, "1", 2], ["R", 2, "..", 2], ["C", 3, "2", 2], ["R", 1, ",", 2], ["C", 0, "0", 2], ["R", 2, "..", 2], ["C", 4, "100", 2], ["R", 8, "]", 2], ["W", 8, "of", 2], ["W", 5, "string", 2], ["R", 4, ";", 2], ["W", 9, "procedure", 4], ["I", 3, "proc1", 4], ["R", 5, "(", 4], ["I", 4, "arg1", 4], ["R", 3, ":", 4], ["W", 3, "integer", 4], ["R", 4, ";", 4], ["I", 5, "arg2", 4], ["R", 3, ":", 4], ["W", 7, "array", 4], ["R", 7, "[", 4], ["C", 0, "0", 4], ["R", 2, "..", 4], ["C", 2, "1", 4], ["R", 1, ",", 4], ["C", 0, "0", 4], ["R", 2, "..", 4], ["C", 5, "4", 4], ["R", 8, "]", 4], ["W", 8, "of", 4], ["W", 4, "real", 4], ["R", 6, ")", 4], ["R", 4, ";", 4], ["W", 1, "var", 5], ["I", 0, "a", 5], ["R", 1, ",", 5], ["I", 1, "b", 5], ["R", 3, ":", 5], ["W", 3, "integer", 5], ["R", 4, ";", 5], ["I", 0, "cs", 6], ["R", 3, ":", 6], ["W", 7, "array", 6], ["R", 7, "[", 6], ["C", 0, "0", 6], ["R", 2, "..", 6], ["C", 1, "20", 6], ["R", 1, ",", 6], ["C", 2, "1", 6], ["R", 2, "..", 6], ["C", 3, "2", 6], ["R", 1, ",", 6], ["C", 0, "0", 6], ["R", 2, "..", 6], ["C", 4, "100", 6], ["R", 8, "]", 6], ["W", 8, "of", 6], ["W", 5, "string", 6], ["R", 4, ";", 6], ["W", 9, "procedure", 8], ["I", 6, "proc2", 8], ["R", 4, ";", 8], ["W", 11, "begin", 9], ["I", 3, "a", 10], ["W", 12, ":=", 10], ["C", 2, "1", 10], ["R", 4, ";", 10], ["W", 17, "end", 11], ["R", 4, ";", 11], ["W", 11, "begin", 12], ["I", 1, "arg1", 13], ["W", 12, ":=", 13], ["I", 2, "arg2", 13], ["R", 4, ";", 13], ["W", 17, "end", 14], ["R", 4, ";", 14], ["W", 10, "function", 16], ["I", 7, "func1", 16], ["R", 5, "(", 16], ["I", 5, "arg1", 16], ["R", 3, ":", 16], ["W", 3, "integer", 16], ["R", 6, ")", 16], ["R", 3, ":", 16], ["W", 3, "integer", 16], ["R", 4, ";", 16], ["W", 11, "begin", 17], ["I", 5, "arg1", 18], ["W", 12, ":=", 18], ["I", 5, "arg1", 18], ["O", 2, "*", 18], ["C", 3, "2", 18], ["R", 4, ";", 18], ["W", 19, "return", 19], ["I", 5, "arg1", 19], ["R", 4, ";", 19], ["I", 5, "arg1", 20], ["W", 12, ":=", 20], ["I", 5, "arg1", 20], ["O", 2, "*", 20], ["C", 3, "2", 20], ["R", 4, ";", 20], ["W", 17, "end", 21], ["R", 4, ";", 21], ["W", 11, "begin", 23], ["I", 4, "a", 24], ["W", 12, ":=", 24], ["C", 2, "1", 24], ["R", 4, ";", 24], ["W", 14, "if", 25], ["C", 6, "5", 25], ["O", 6, ">", 25], ["C", 0, "0", 25], ["W", 15, "then", 25], ["I", 4, "a", 25], ["W", 12, ":=", 25], ["C", 2, "1", 25], ["R", 4, ";", 25], ["W", 16, "else", 25], ["I", 4, "a", 25], ["W", 12, ":=", 25], ["C", 3, "2", 25], ["R", 4, ";", 25], ["I", 4, "a", 26], ["W", 12, ":=", 26], ["C", 3, "2", 26], ["R", 4, ";", 26], ["W", 18, "end.", 27]], "tables": {"service_words": ["program", "var", "const", "integer", "real", "string", "label", "array", "of", "procedure", "function", "begin", ":=", "goto", "if", "then", "else", "end", "end.", "return", "while"], "operations": ["+", "-", "*", "/", "^", "<", ">", "=", "<>", "<=", ">="], "separators": [" ", ",", "..", ":", ";", "(", ")", "[", "]", "{", "}", "'"], "constants": [{"type": "integer", "value": "0"}, {"type": "integer", "value": "20"}, {"type": "integer", "value": "1"}, {"type": "integer", "value": "2"}, {"type": "integer", "value": "100"}, {"type": "integer", "value": "4"}, {"type": "integer", "value": "5"}], "identifiers": [{"type": "procedure", "name": "proc1", "number_of_procedure": 0, "level_of_procedure": 0, "number_in_procedure": 0}, {"type": "integer", "name": "b", "number_of_procedure": 0, "level_of_procedure": 0, "number_in_procedure": 0}, {"type": "string_array", "name": "cs", "number_of_procedure": 0, "level_of_procedure": 0, "number_in_procedure": 0}, {"type": "identifier", "name": "proc2", "number_of_procedure": 0, "level_of_procedure": 0, "number_in_procedure": 0}, {"type": "identifier", "name": "a", "number_of_procedure": 0, "level_of_procedure": 0, "number_in_procedure": 0}, {"type": "identifier", "name": "arg1", "number_of_procedure": 0, "level_of_procedure": 0, "number_in_procedure": 0}, {"type": "identifier", "name": "arg2", "number_of_procedure": 0, "level_of_procedure": 0, "number_in_procedure": 0}, {"type": "function", "name": "func1", "number_of_procedure": 0, "level_of_procedure": 0, "number_in_procedure": 0}]}}